woe_bin/__init__.py
woe_bin/__version__.py
woe_bin/linear_woe_bin.py
woe_linear_bin-0.0.2.dist-info/LICENSE
woe_linear_bin-0.0.2.dist-info/METADATA
woe_linear_bin-0.0.2.dist-info/WHEEL
woe_linear_bin-0.0.2.dist-info/entry_points.txt
woe_linear_bin-0.0.2.dist-info/top_level.txt
woe_linear_bin-0.0.2.dist-info/RECORD
